kivy_deps/__init__.py
kivy_deps/gstreamer/__init__.py
kivy_deps_gstreamer-0.3.4.data/data/share/gstreamer/bin/avcodec-58.dll
kivy_deps_gstreamer-0.3.4.data/data/share/gstreamer/bin/avfilter-7.dll
kivy_deps_gstreamer-0.3.4.data/data/share/gstreamer/bin/avformat-58.dll
kivy_deps_gstreamer-0.3.4.data/data/share/gstreamer/bin/avutil-56.dll
kivy_deps_gstreamer-0.3.4.data/data/share/gstreamer/bin/bz2.dll
kivy_deps_gstreamer-0.3.4.data/data/share/gstreamer/bin/bz2.pdb
kivy_deps_gstreamer-0.3.4.data/data/share/gstreamer/bin/ffi-7.dll
kivy_deps_gstreamer-0.3.4.data/data/share/gstreamer/bin/ffi-7.pdb
kivy_deps_gstreamer-0.3.4.data/data/share/gstreamer/bin/fribidi-0.dll
kivy_deps_gstreamer-0.3.4.data/data/share/gstreamer/bin/fribidi-0.pdb
kivy_deps_gstreamer-0.3.4.data/data/share/gstreamer/bin/fribidi.pdb
kivy_deps_gstreamer-0.3.4.data/data/share/gstreamer/bin/gdbus-codegen
kivy_deps_gstreamer-0.3.4.data/data/share/gstreamer/bin/gdbus.exe
kivy_deps_gstreamer-0.3.4.data/data/share/gstreamer/bin/gdbus.pdb
kivy_deps_gstreamer-0.3.4.data/data/share/gstreamer/bin/gdk-pixbuf-csource.exe
kivy_deps_gstreamer-0.3.4.data/data/share/gstreamer/bin/gdk-pixbuf-csource.pdb
kivy_deps_gstreamer-0.3.4.data/data/share/gstreamer/bin/gdk-pixbuf-query-loaders.exe
kivy_deps_gstreamer-0.3.4.data/data/share/gstreamer/bin/gdk-pixbuf-query-loaders.pdb
kivy_deps_gstreamer-0.3.4.data/data/share/gstreamer/bin/gdk_pixbuf-2.0-0.dll
kivy_deps_gstreamer-0.3.4.data/data/share/gstreamer/bin/gdk_pixbuf-2.0-0.pdb
kivy_deps_gstreamer-0.3.4.data/data/share/gstreamer/bin/ges-1.0-0.dll
kivy_deps_gstreamer-0.3.4.data/data/share/gstreamer/bin/ges-1.0-0.pdb
kivy_deps_gstreamer-0.3.4.data/data/share/gstreamer/bin/ges-launch-1.0.exe
kivy_deps_gstreamer-0.3.4.data/data/share/gstreamer/bin/ges-launch-1.0.pdb
kivy_deps_gstreamer-0.3.4.data/data/share/gstreamer/bin/gio-2.0-0.dll
kivy_deps_gstreamer-0.3.4.data/data/share/gstreamer/bin/gio-2.0-0.pdb
kivy_deps_gstreamer-0.3.4.data/data/share/gstreamer/bin/gio-querymodules.exe
kivy_deps_gstreamer-0.3.4.dist-info/METADATA
kivy_deps_gstreamer-0.3.4.dist-info/WHEEL
kivy_deps_gstreamer-0.3.4.dist-info/top_level.txt
kivy_deps_gstreamer-0.3.4.dist-info/RECORD
